signalp/__init__.py
signalp/__main__.py
signalp/make_output_files.py
signalp/make_sequence_plot.py
signalp/predict.py
signalp/sequential_model.py
signalp/utils.py
signalp/conversion_utils/__init__.py
signalp/conversion_utils/move_checkpoint_to_device.py
signalp/model_weights/README.md
signalp6-6.0.data/scripts/signalp6_convert_models
signalp6-6.0.dist-info/METADATA
signalp6-6.0.dist-info/WHEEL
signalp6-6.0.dist-info/entry_points.txt
signalp6-6.0.dist-info/top_level.txt
signalp6-6.0.dist-info/RECORD
