Metadata-Version: 2.1
Name: signalp6
Version: 6.0
Summary: SignalP 6.0 signal peptide prediction tool
Home-page: https://www.healthtech.dtu.dk/
Author: Felix Teufel
Author-email: felix.teufel@gmail.com
Requires-Python: >=3.6, <4
Requires-Dist: matplotlib (>3.3.2)
Requires-Dist: numpy (>1.19.2)
Requires-Dist: torch (>1.7.0)
Requires-Dist: tqdm (>4.46.1)
